ChangeLog.rst
LICENSE
MANIFEST.in
README.rst
setup.cfg
setup.py
src/zbarlight/__init__.py
src/zbarlight/_zbarlight.c
src/zbarlight.egg-info/PKG-INFO
src/zbarlight.egg-info/SOURCES.txt
src/zbarlight.egg-info/dependency_links.txt
src/zbarlight.egg-info/not-zip-safe
src/zbarlight.egg-info/requires.txt
src/zbarlight.egg-info/top_level.txt